LICENSE
README.md
micro_config.py
setup.cfg
setup.py
micro_config.egg-info/PKG-INFO
micro_config.egg-info/SOURCES.txt
micro_config.egg-info/dependency_links.txt
micro_config.egg-info/top_level.txt