Metadata-Version: 2.1
Name: micro-config
Version: 0.1.3
Summary: A deep learning config framework based on hierarchical dataclasses.
Home-page: https://github.com/Sea-Snell/micro_config
Author: Charlie Snell
Author-email: csnell22@berkeley.edu
License: MIT
Keywords: configs configuration dataclasses deeplearning hierarchy hierarchical
Classifier: Development Status :: 3 - Alpha
Classifier: Topic :: Scientific/Engineering :: Artificial Intelligence
Requires-Python: >=3
License-File: LICENSE
